py_mini_racer/__about__.py
py_mini_racer/__init__.py
py_mini_racer/libmini_racer.glibc.so
py_mini_racer/py_mini_racer.py
py_mini_racer-0.6.0.dist-info/AUTHORS.rst
py_mini_racer-0.6.0.dist-info/LICENSE
py_mini_racer-0.6.0.dist-info/METADATA
py_mini_racer-0.6.0.dist-info/WHEEL
py_mini_racer-0.6.0.dist-info/top_level.txt
py_mini_racer-0.6.0.dist-info/RECORD
