Metadata-Version: 2.1
Name: py-mini-racer
Version: 0.6.0
Summary: Minimal, modern embedded V8 for Python.
Home-page: https://github.com/sqreen/PyMiniRacer
Author: Sqreen
Author-email: support@sqreen.com
License: ISCL
Keywords: py_mini_racer
Platform: UNKNOWN
Classifier: Development Status :: 5 - Production/Stable
Classifier: Intended Audience :: Developers
Classifier: License :: OSI Approved :: ISC License (ISCL)
Classifier: Natural Language :: English
Classifier: Programming Language :: Python :: 2
Classifier: Programming Language :: Python :: 2.7
Classifier: Programming Language :: Python :: 3
